whenareyou/__init__.py
whenareyou/airports.csv
whenareyou-0.3.2.dist-info/DESCRIPTION.rst
whenareyou-0.3.2.dist-info/METADATA
whenareyou-0.3.2.dist-info/RECORD
whenareyou-0.3.2.dist-info/WHEEL
whenareyou-0.3.2.dist-info/metadata.json
whenareyou-0.3.2.dist-info/top_level.txt
