Metadata-Version: 1.0
Name: whenareyou
Version: 0.3.2
Summary: Gets the timezone of any location in the world
Home-page: https://github.com/aerupt/whenareyou
Author: Lasse Schuirmann
Author-email: lasse.schuirmann@gmail.com
License: MIT
Platform: UNKNOWN
